hikari_shim/__init__.py
hikari_shim/py.typed
hikari_shim-1.0.3.dist-info/LICENSE
hikari_shim-1.0.3.dist-info/WHEEL
hikari_shim-1.0.3.dist-info/METADATA
hikari_shim-1.0.3.dist-info/RECORD
