Metadata-Version: 2.1
Name: hikari_shim
Version: 1.0.3
Summary: A compatability shim between Discord.py and Hikari.
Author-email: A5rocks <git@helvetica.moe>
Requires-Python: >=3.8
Classifier: License :: OSI Approved :: MIT License
Requires-Dist: hikari
Requires-Dist: discord.py ; extra == "dev"
Requires-Dist: mypy ; extra == "dev"
Requires-Dist: isort ; extra == "dev"
Requires-Dist: black ; extra == "dev"
Project-URL: Home, https://github.com/A5rocks/hikari-dpy-shim
Provides-Extra: dev
